bnf_string_generator/__init__.py
bnf_string_generator-0.1.0.dist-info/METADATA
bnf_string_generator-0.1.0.dist-info/WHEEL
bnf_string_generator-0.1.0.dist-info/licenses/LICENSE
bnf_string_generator-0.1.0.dist-info/RECORD
