Metadata-Version: 2.3
Name: bnf-string-generator
Version: 0.1.0
Summary: A tool for generating random strings based on Backus-Naur Form (BNF) grammar.
Project-URL: Homepage, https://github.com/romelium/bnf-string-generator
Project-URL: Issues, https://github.com/romelium/bnf-string-generator/issues
Author-email: Romelium <romeomanzanillaiii@gmail.com>
License: MIT
Keywords: BNF,generator,grammar,random,string
Classifier: Development Status :: 5 - Production/Stable
Classifier: Intended Audience :: Developers
Classifier: Intended Audience :: Education
Classifier: Intended Audience :: Science/Research
Classifier: License :: OSI Approved :: MIT License
Classifier: Programming Language :: Python :: 3
Classifier: Programming Language :: Python :: 3.6
Classifier: Programming Language :: Python :: 3.7
Classifier: Programming Language :: Python :: 3.8
Classifier: Programming Language :: Python :: 3.9
Classifier: Programming Language :: Python :: 3.10
Classifier: Programming Language :: Python :: 3.11
Classifier: Topic :: Education
Classifier: Topic :: Education :: Computer Aided Instruction (CAI)
Classifier: Topic :: Software Development :: Code Generators
Classifier: Topic :: Software Development :: Libraries :: Python Modules
Classifier: Topic :: Text Processing
